MANIFEST.in
setup.py
cbmock/__init__.py
cbmock/cbmock.py
cbmock/helpers.py
cbmock/httpmock.py
cbmock/logging.conf
cbmock/mcbackend.py
cbmock/mcmock.py
cbmock/smartserver.py
cbmock.egg-info/PKG-INFO
cbmock.egg-info/SOURCES.txt
cbmock.egg-info/dependency_links.txt
cbmock.egg-info/entry_points.txt
cbmock.egg-info/requires.txt
cbmock.egg-info/top_level.txt